<annotation>
	<folder>train</folder>
	<filename>IMG_20190724_152222.jpg</filename>
	<path>C:\Users\poorn\Documents\Tensorflow\models\research\object_detection\images\train\IMG_20190724_152222.jpg</path>
	<source>
		<database>Unknown</database>
	</source>
	<size>
		<width>800</width>
		<height>600</height>
		<depth>3</depth>
	</size>
	<segmented>0</segmented>
	<object>
		<name>piston</name>
		<pose>Unspecified</pose>
		<truncated>0</truncated>
		<difficult>0</difficult>
		<bndbox>
			<xmin>49</xmin>
			<ymin>151</ymin>
			<xmax>769</xmax>
			<ymax>470</ymax>
		</bndbox>
	</object>
</annotation>
